LICENSE
MANIFEST.in
README.md
setup.cfg
setup.py
django_contrib/.DS_Store
django_contrib/__init__.py
django_contrib/__pycache__/__init__.cpython-39.pyc
django_contrib/environment_vars/.DS_Store
django_contrib/environment_vars/__init__.py
django_contrib/environment_vars/admin.py
django_contrib/environment_vars/apps.py
django_contrib/environment_vars/models.py
django_contrib/environment_vars/tests.py
django_contrib/environment_vars/urls.py
django_contrib/environment_vars/views.py
django_contrib/environment_vars/__pycache__/__init__.cpython-39.pyc
django_contrib/environment_vars/__pycache__/admin.cpython-39.pyc
django_contrib/environment_vars/__pycache__/apps.cpython-39.pyc
django_contrib/environment_vars/__pycache__/models.cpython-39.pyc
django_contrib/environment_vars/__pycache__/tests.cpython-39.pyc
django_contrib/environment_vars/__pycache__/urls.cpython-39.pyc
django_contrib/environment_vars/__pycache__/views.cpython-39.pyc
django_contrib/environment_vars/migrations/__init__.py
django_contrib/environment_vars/migrations/__pycache__/__init__.cpython-39.pyc
django_contrib/environment_vars/templates/.DS_Store
django_contrib/environment_vars/templates/mainws/index.html
django_environment_vars.egg-info/PKG-INFO
django_environment_vars.egg-info/SOURCES.txt
django_environment_vars.egg-info/dependency_links.txt
django_environment_vars.egg-info/requires.txt
django_environment_vars.egg-info/top_level.txt