Metadata-Version: 2.1
Name: django-environment-vars
Version: 0.1056b0
Summary: A Django environment variables manager.
Home-page: https://github.com/bygregonline/django-env-public/
Author: Greg Flores
Author-email: bygregonline@yaho.com
License: MIT
Project-URL: Documentation, https://github.com/bygregonline/django-env-public
Project-URL: Funding, https://donate.pypi.org
Project-URL: Source, https://github.com/bygregonline/django-env-public/src
Project-URL: Tracker, https://github.com/bygregonline/django-env-public/issues
Platform: UNKNOWN
Classifier: Environment :: Web Environment
Classifier: Framework :: Django
Classifier: Framework :: Django :: 3.2
Classifier: Intended Audience :: Developers
Classifier: License :: OSI Approved :: BSD License
Classifier: Operating System :: OS Independent
Classifier: Programming Language :: Python :: 3.6
Classifier: Programming Language :: Python :: 3.7
Classifier: Programming Language :: Python :: 3.8
Classifier: Programming Language :: Python :: 3.9
Classifier: Topic :: Internet :: WWW/HTTP
Classifier: Topic :: Internet :: WWW/HTTP :: Dynamic Content
Requires-Python: >=3.6
License-File: LICENSE
